IdnsBotCh/__init__.py
IdnsBotCh-1.1.9.dist-info/LICENSE.txt
IdnsBotCh-1.1.9.dist-info/METADATA
IdnsBotCh-1.1.9.dist-info/WHEEL
IdnsBotCh-1.1.9.dist-info/top_level.txt
IdnsBotCh-1.1.9.dist-info/RECORD
